datalad_webapp/__init__.py
datalad_webapp/resource.py
datalad_webapp/examples/__init__.py
datalad_webapp/resources/__init__.py
datalad_webapp/resources/auth.py
datalad_webapp/resources/file.py
datalad_webapp/resources/procedure.py
datalad_webapp/resources/subdataset.py
datalad_webapp/tests/__init__.py
datalad_webapp/tests/helpers.py
datalad_webapp/tests/test_file.py
datalad_webapp/tests/test_procedure.py
datalad_webapp/tests/test_register.py
datalad_webapp/tests/test_server.py
datalad_webapp-0.3.dist-info/COPYING
datalad_webapp-0.3.dist-info/METADATA
datalad_webapp-0.3.dist-info/WHEEL
datalad_webapp-0.3.dist-info/entry_points.txt
datalad_webapp-0.3.dist-info/top_level.txt
datalad_webapp-0.3.dist-info/RECORD
